aws_coco/__init__.py
aws_coco/lib/__init__.py
aws_coco/lib/aws.py
aws_coco/lib/firefox.py
aws_coco/lib/utils.py
aws_coco/main.py
aws_coco-0.1.7.dist-info/entry_points.txt
aws_coco-0.1.7.dist-info/WHEEL
aws_coco-0.1.7.dist-info/METADATA
aws_coco-0.1.7.dist-info/RECORD
