Metadata-Version: 2.1
Name: aws-coco
Version: 0.1.7
Summary: A utility for managing AWS Console Sessions with Firefox Containers
Home-page: https://github.com/wulfmann/aws-coco
License: MIT
Keywords: aws,firefox containers,aws console,console container
Author: Joe Snell
Author-email: joepsnell@gmail.com
Requires-Python: >=3.8,<4.0
Classifier: License :: OSI Approved :: MIT License
Classifier: Programming Language :: Python :: 3
Classifier: Programming Language :: Python :: 3.8
Requires-Dist: boto3 (>=1.15.10,<2.0.0)
Requires-Dist: requests (>=2.24.0,<3.0.0)
Project-URL: Documentation, https://github.com/wulfmann/aws-coco/README.md
Project-URL: Repository, https://github.com/wulfmann/aws-coco
Project-URL: issues, https://github.com/wulfmann/aws-coco/issues
